flask_dbhealthcheck.py
Flask_dbhealthcheck-0.3.dist-info/LICENSE
Flask_dbhealthcheck-0.3.dist-info/METADATA
Flask_dbhealthcheck-0.3.dist-info/WHEEL
Flask_dbhealthcheck-0.3.dist-info/top_level.txt
Flask_dbhealthcheck-0.3.dist-info/RECORD
