Metadata-Version: 2.1
Name: Flask-dbhealthcheck
Version: 0.3
Summary: Database healthcheck for your Flask app
Home-page: http://example.com/flask-dbhealthcheck/
Author: Abhirag Awasthi
Author-email: abhirag.awasthi@shuttl.com
License: MIT
Platform: any
Classifier: Environment :: Web Environment
Classifier: Intended Audience :: Developers
Classifier: License :: OSI Approved :: MIT License
Classifier: Operating System :: OS Independent
Classifier: Programming Language :: Python :: 3
Classifier: Topic :: Internet :: WWW/HTTP :: Dynamic Content
Classifier: Topic :: Software Development :: Libraries :: Python Modules
Requires-Dist: Flask
